.hgignore
CHANGES.rst
LICENSE.txt
MANIFEST.in
README.rst
bootstrap.py
buildout.cfg
setup.py
js/__init__.py
js.graphael.egg-info/PKG-INFO
js.graphael.egg-info/SOURCES.txt
js.graphael.egg-info/dependency_links.txt
js.graphael.egg-info/entry_points.txt
js.graphael.egg-info/namespace_packages.txt
js.graphael.egg-info/not-zip-safe
js.graphael.egg-info/requires.txt
js.graphael.egg-info/top_level.txt
js/graphael/__init__.py
js/graphael/test_graphael.txt
js/graphael/resources/README.txt
js/graphael/resources/g.bar-min.js
js/graphael/resources/g.bar.js
js/graphael/resources/g.dot-min.js
js/graphael/resources/g.dot.js
js/graphael/resources/g.line-min.js
js/graphael/resources/g.line.js
js/graphael/resources/g.pie-min.js
js/graphael/resources/g.pie.js
js/graphael/resources/g.raphael-min.js
js/graphael/resources/g.raphael.js