Metadata-Version: 1.0
Name: js.graphael
Version: 0.5.1
Summary: Fanstatic packaging of gRaphaël
Home-page: https://bitbucket.org/gocept/js.graphael
Author: gocept Developers
Author-email: mail@gocept.com
License: BSD
Platform: UNKNOWN
